pointclass/__init__.py
pointclass-1.6.dist-info/METADATA
pointclass-1.6.dist-info/WHEEL
pointclass-1.6.dist-info/licence.txt.txt
pointclass-1.6.dist-info/top_level.txt
pointclass-1.6.dist-info/RECORD
