Metadata-Version: 2.1
Name: pointclass
Version: 1.6
Summary: this is mathematics perps lybrary
Author: xxxxxx
License-File: licence.txt.txt
